autofmt/__init__.py
autofmt/py.typed
autofmt/configurations/__init__.py
autofmt/configurations/load_config.py
autofmt/services/__init__.py
autofmt/services/formatter.py
autofmt/services/get_relative_path.py
autofmt/services/logger.py
autofmt/services/watcher.py
autofmt-0.1.1.dist-info/METADATA
autofmt-0.1.1.dist-info/WHEEL
autofmt-0.1.1.dist-info/entry_points.txt
autofmt-0.1.1.dist-info/licenses/LICENSE
autofmt-0.1.1.dist-info/RECORD
