Metadata-Version: 2.4
Name: autofmt
Version: 0.1.1
Summary: Watchdog-based Python auto-formatter using Ruff and Black
Project-URL: Homepage, https://github.com/shaileshpandit141/autofmt
Project-URL: Repository, https://github.com/shaileshpandit141/autofmt
Project-URL: Issues, https://github.com/shaileshpandit141/autofmt/issues
Author-email: shaileshpandit141 <shaileshpandit141@gmail.com>
License: # MIT License
License-File: LICENSE
Classifier: Development Status :: 4 - Beta
Classifier: Environment :: Console
Classifier: Intended Audience :: Developers
Classifier: License :: OSI Approved :: MIT License
Classifier: Operating System :: OS Independent
Classifier: Programming Language :: Python
Classifier: Programming Language :: Python :: 3.10
Classifier: Programming Language :: Python :: 3.11
Classifier: Programming Language :: Python :: 3.12
Classifier: Programming Language :: Python :: 3.13
Classifier: Topic :: Software Development :: Build Tools
Classifier: Topic :: Software Development :: Code Generators
Classifier: Topic :: Software Development :: Quality Assurance
Classifier: Topic :: Utilities
Requires-Python: >=3.13
Requires-Dist: black>=25.1.0
Requires-Dist: rich>=14.1.0
Requires-Dist: ruff>=0.12.5
Requires-Dist: watchdog>=6.0.0
Provides-Extra: dev
Requires-Dist: black; extra == 'dev'
Requires-Dist: pytest; extra == 'dev'
Requires-Dist: ruff; extra == 'dev'
